metacatalog_client/__init__.py
metacatalog_client/__version__.py
metacatalog_client/client.py
metacatalog_client/output.py
metacatalog_client-0.1.4.dist-info/LICENSE
metacatalog_client-0.1.4.dist-info/METADATA
metacatalog_client-0.1.4.dist-info/WHEEL
metacatalog_client-0.1.4.dist-info/top_level.txt
metacatalog_client-0.1.4.dist-info/RECORD
