Metadata-Version: 2.2
Name: metacatalog_client
Version: 0.1.4
Summary: Python client for MetaCatalog server instances
Author: Mirko Mälicke
Author-email: mirko.malicke@kit.edu
License: GPLv3
License-File: LICENSE
Requires-Dist: httpx
Requires-Dist: pydantic
Dynamic: author
Dynamic: author-email
Dynamic: description
Dynamic: description-content-type
Dynamic: license
Dynamic: requires-dist
Dynamic: summary
